{
  "schema": "twfoundry.tdx.citybus.snapshot.v1",
  "source": {
    "provider": "TDX",
    "dataset": "Historical.Bus.RealTimeByFrequency.City",
    "city": "Taipei",
    "mode": "tdx-historical"
  },
  "captureDate": "2026-05-20",
  "capturedAt": "2026-05-19T22:50:00.000Z",
  "slot": {
    "key": "2026-05-20T06:50+08:00",
    "date": "2026-05-20",
    "timeLabel": "06:50",
    "intervalMinutes": 5,
    "timeZone": "Asia/Taipei"
  },
  "count": 149,
  "routeCount": 19,
  "bounds": {
    "minLat": 24.958932,
    "maxLat": 25.143622,
    "minLon": 121.424112,
    "maxLon": 121.638007
  },
  "records": [
    {
      "PlateNumb": "EAL-3079",
      "RouteUID": "TPE10241",
      "RouteName": "藍36",
      "Direction": 1,
      "BusPosition": {
        "PositionLat": 25.060218,
        "PositionLon": 121.627073
      },
      "Speed": 36,
      "Azimuth": 224,
      "GPSTime": "2026-05-20T06:54:47+08:00",
      "UpdateTime": "2026-05-20T06:54:55+08:00",
      "source": "TDX Historical Bus RealTimeByFrequency City Taipei",
      "freshness": "fresh",
      "completeness": 1,
      "mode": "tdx-historical",
      "age": "0s",
      "x": "87.71%",
      "y": "46.51%"
    },
    {
      "PlateNumb": "EAL-3075",
      "RouteUID": "TPE10241",
      "RouteName": "藍36",
      "Direction": 0,
      "BusPosition": {
        "PositionLat": 25.063232,
        "PositionLon": 121.631322
      },
      "Speed": 33,
      "Azimuth": 55,
      "GPSTime": "2026-05-20T06:54:44+08:00",
      "UpdateTime": "2026-05-20T06:54:55+08:00",
      "source": "TDX Historical Bus RealTimeByFrequency City Taipei",
      "freshness": "fresh",
      "completeness": 1,
      "mode": "tdx-historical",
      "age": "0s",
      "x": "89.37%",
      "y": "45.34%"
    },
    {
      "PlateNumb": "EAL-3175",
      "RouteUID": "TPE10251",
      "RouteName": "南京幹線",
      "Direction": 0,
      "BusPosition": {
        "PositionLat": 25.052187,
        "PositionLon": 121.521965
      },
      "Speed": 38,
      "Azimuth": 279,
      "GPSTime": "2026-05-20T06:54:48+08:00",
      "UpdateTime": "2026-05-20T06:54:55+08:00",
      "source": "TDX Historical Bus RealTimeByFrequency City Taipei",
      "freshness": "fresh",
      "completeness": 1,
      "mode": "tdx-historical",
      "age": "0s",
      "x": "46.43%",
      "y": "49.65%"
    },
    {
      "PlateNumb": "EAL-3179",
      "RouteUID": "TPE10251",
      "RouteName": "南京幹線",
      "Direction": 1,
      "BusPosition": {
        "PositionLat": 25.057815,
        "PositionLon": 121.600803
      },
      "Speed": 0,
      "Azimuth": 158,
      "GPSTime": "2026-05-20T06:54:48+08:00",
      "UpdateTime": "2026-05-20T06:54:55+08:00",
      "source": "TDX Historical Bus RealTimeByFrequency City Taipei",
      "freshness": "fresh",
      "completeness": 1,
      "mode": "tdx-historical",
      "age": "0s",
      "x": "77.39%",
      "y": "47.45%"
    },
    {
      "PlateNumb": "EAL-3193",
      "RouteUID": "TPE10251",
      "RouteName": "南京幹線",
      "Direction": 0,
      "BusPosition": {
        "PositionLat": 25.059703,
        "PositionLon": 121.614303
      },
      "Speed": 0,
      "Azimuth": 11,
      "GPSTime": "2026-05-20T06:54:41+08:00",
      "UpdateTime": "2026-05-20T06:54:55+08:00",
      "source": "TDX Historical Bus RealTimeByFrequency City Taipei",
      "freshness": "fresh",
      "completeness": 1,
      "mode": "tdx-historical",
      "age": "0s",
      "x": "82.69%",
      "y": "46.72%"
    },
    {
      "PlateNumb": "EAL-3172",
      "RouteUID": "TPE10253",
      "RouteName": "內科通勤專車22",
      "Direction": 0,
      "BusPosition": {
        "PositionLat": 25.077877,
        "PositionLon": 121.529645
      },
      "Speed": 32,
      "Azimuth": 84,
      "GPSTime": "2026-05-20T06:54:48+08:00",
      "UpdateTime": "2026-05-20T06:54:55+08:00",
      "source": "TDX Historical Bus RealTimeByFrequency City Taipei",
      "freshness": "fresh",
      "completeness": 1,
      "mode": "tdx-historical",
      "age": "0s",
      "x": "49.44%",
      "y": "39.63%"
    },
    {
      "PlateNumb": "EAL-3199",
      "RouteUID": "TPE10251",
      "RouteName": "南京幹線",
      "Direction": 1,
      "BusPosition": {
        "PositionLat": 25.05803,
        "PositionLon": 121.597257
      },
      "Speed": 0,
      "Azimuth": 308,
      "GPSTime": "2026-05-20T06:54:48+08:00",
      "UpdateTime": "2026-05-20T06:54:55+08:00",
      "source": "TDX Historical Bus RealTimeByFrequency City Taipei",
      "freshness": "fresh",
      "completeness": 1,
      "mode": "tdx-historical",
      "age": "0s",
      "x": "76.00%",
      "y": "47.37%"
    },
    {
      "PlateNumb": "EAL-3200",
      "RouteUID": "TPE10251",
      "RouteName": "南京幹線",
      "Direction": 1,
      "BusPosition": {
        "PositionLat": 25.057912,
        "PositionLon": 121.60082
      },
      "Speed": 0,
      "Azimuth": 109,
      "GPSTime": "2026-05-20T06:54:40+08:00",
      "UpdateTime": "2026-05-20T06:54:55+08:00",
      "source": "TDX Historical Bus RealTimeByFrequency City Taipei",
      "freshness": "fresh",
      "completeness": 1,
      "mode": "tdx-historical",
      "age": "0s",
      "x": "77.40%",
      "y": "47.41%"
    },
    {
      "PlateNumb": "478-U5",
      "RouteUID": "TPE10262",
      "RouteName": "2",
      "Direction": 1,
      "BusPosition": {
        "PositionLat": 25.089545,
        "PositionLon": 121.50324
      },
      "Speed": 37,
      "Azimuth": 288,
      "GPSTime": "2026-05-20T06:54:47+08:00",
      "UpdateTime": "2026-05-20T06:54:55+08:00",
      "source": "TDX Historical Bus RealTimeByFrequency City Taipei",
      "freshness": "fresh",
      "completeness": 1,
      "mode": "tdx-historical",
      "age": "0s",
      "x": "39.07%",
      "y": "35.08%"
    },
    {
      "PlateNumb": "EAL-2071",
      "RouteUID": "TPE10292",
      "RouteName": "藍10",
      "Direction": 1,
      "BusPosition": {
        "PositionLat": 25.037805,
        "PositionLon": 121.591353
      },
      "Speed": 30,
      "Azimuth": 189,
      "GPSTime": "2026-05-20T06:54:43+08:00",
      "UpdateTime": "2026-05-20T06:54:55+08:00",
      "source": "TDX Historical Bus RealTimeByFrequency City Taipei",
      "freshness": "fresh",
      "completeness": 1,
      "mode": "tdx-historical",
      "age": "0s",
      "x": "73.68%",
      "y": "55.25%"
    },
    {
      "PlateNumb": "EAA-052",
      "RouteUID": "TPE10231",
      "RouteName": "民權幹線",
      "Direction": 1,
      "BusPosition": {
        "PositionLat": 25.062087,
        "PositionLon": 121.544778
      },
      "Speed": 38,
      "Azimuth": 96,
      "GPSTime": "2026-05-20T06:54:49+08:00",
      "UpdateTime": "2026-05-20T06:54:55+08:00",
      "source": "TDX Historical Bus RealTimeByFrequency City Taipei",
      "freshness": "fresh",
      "completeness": 1,
      "mode": "tdx-historical",
      "age": "0s",
      "x": "55.39%",
      "y": "45.79%"
    },
    {
      "PlateNumb": "EAL-3189",
      "RouteUID": "TPE10251",
      "RouteName": "南京幹線",
      "Direction": 0,
      "BusPosition": {
        "PositionLat": 25.07707,
        "PositionLon": 121.600565
      },
      "Speed": 35,
      "Azimuth": 340,
      "GPSTime": "2026-05-20T06:54:43+08:00",
      "UpdateTime": "2026-05-20T06:54:55+08:00",
      "source": "TDX Historical Bus RealTimeByFrequency City Taipei",
      "freshness": "fresh",
      "completeness": 1,
      "mode": "tdx-historical",
      "age": "0s",
      "x": "77.30%",
      "y": "39.94%"
    },
    {
      "PlateNumb": "EAL-3183",
      "RouteUID": "TPE10251",
      "RouteName": "南京幹線",
      "Direction": 0,
      "BusPosition": {
        "PositionLat": 25.05142,
        "PositionLon": 121.565702
      },
      "Speed": 35,
      "Azimuth": 269,
      "GPSTime": "2026-05-20T06:54:43+08:00",
      "UpdateTime": "2026-05-20T06:54:55+08:00",
      "source": "TDX Historical Bus RealTimeByFrequency City Taipei",
      "freshness": "fresh",
      "completeness": 1,
      "mode": "tdx-historical",
      "age": "0s",
      "x": "63.60%",
      "y": "49.94%"
    },
    {
      "PlateNumb": "556-U5",
      "RouteUID": "TPE10181",
      "RouteName": "205",
      "Direction": 1,
      "BusPosition": {
        "PositionLat": 25.046908,
        "PositionLon": 121.514175
      },
      "Speed": 46,
      "Azimuth": 105,
      "GPSTime": "2026-05-20T06:54:48+08:00",
      "UpdateTime": "2026-05-20T06:54:55+08:00",
      "source": "TDX Historical Bus RealTimeByFrequency City Taipei",
      "freshness": "fresh",
      "completeness": 1,
      "mode": "tdx-historical",
      "age": "0s",
      "x": "43.37%",
      "y": "51.70%"
    },
    {
      "PlateNumb": "EAL-3197",
      "RouteUID": "TPE10251",
      "RouteName": "南京幹線",
      "Direction": 1,
      "BusPosition": {
        "PositionLat": 25.059178,
        "PositionLon": 121.58559
      },
      "Speed": 26,
      "Azimuth": 65,
      "GPSTime": "2026-05-20T06:54:49+08:00",
      "UpdateTime": "2026-05-20T06:54:55+08:00",
      "source": "TDX Historical Bus RealTimeByFrequency City Taipei",
      "freshness": "fresh",
      "completeness": 1,
      "mode": "tdx-historical",
      "age": "0s",
      "x": "71.42%",
      "y": "46.92%"
    },
    {
      "PlateNumb": "EAL-1657",
      "RouteUID": "TPE10241",
      "RouteName": "藍36",
      "Direction": 1,
      "BusPosition": {
        "PositionLat": 25.063222,
        "PositionLon": 121.623367
      },
      "Speed": 0,
      "Azimuth": 352,
      "GPSTime": "2026-05-20T06:54:47+08:00",
      "UpdateTime": "2026-05-20T06:54:55+08:00",
      "source": "TDX Historical Bus RealTimeByFrequency City Taipei",
      "freshness": "fresh",
      "completeness": 1,
      "mode": "tdx-historical",
      "age": "0s",
      "x": "86.25%",
      "y": "45.34%"
    },
    {
      "PlateNumb": "373-FZ",
      "RouteUID": "TPE10283",
      "RouteName": "235",
      "Direction": 0,
      "BusPosition": {
        "PositionLat": 25.0246,
        "PositionLon": 121.547063
      },
      "Speed": 37,
      "Azimuth": 96,
      "GPSTime": "2026-05-20T06:54:46+08:00",
      "UpdateTime": "2026-05-20T06:54:55+08:00",
      "source": "TDX Historical Bus RealTimeByFrequency City Taipei",
      "freshness": "fresh",
      "completeness": 1,
      "mode": "tdx-historical",
      "age": "0s",
      "x": "56.28%",
      "y": "60.40%"
    },
    {
      "PlateNumb": "EAL-2089",
      "RouteUID": "TPE10132",
      "RouteName": "234",
      "Direction": 0,
      "BusPosition": {
        "PositionLat": 25.012148,
        "PositionLon": 121.444498
      },
      "Speed": 0,
      "Azimuth": 26,
      "GPSTime": "2026-05-20T06:54:44+08:00",
      "UpdateTime": "2026-05-20T06:54:55+08:00",
      "source": "TDX Historical Bus RealTimeByFrequency City Taipei",
      "freshness": "fresh",
      "completeness": 1,
      "mode": "tdx-historical",
      "age": "0s",
      "x": "16.01%",
      "y": "65.25%"
    },
    {
      "PlateNumb": "EAL-2183",
      "RouteUID": "TPE10142",
      "RouteName": "南環幹線",
      "Direction": 1,
      "BusPosition": {
        "PositionLat": 24.971447,
        "PositionLon": 121.54269
      },
      "Speed": 6,
      "Azimuth": 181,
      "GPSTime": "2026-05-20T06:54:42+08:00",
      "UpdateTime": "2026-05-20T06:54:55+08:00",
      "source": "TDX Historical Bus RealTimeByFrequency City Taipei",
      "freshness": "fresh",
      "completeness": 1,
      "mode": "tdx-historical",
      "age": "0s",
      "x": "54.57%",
      "y": "81.12%"
    },
    {
      "PlateNumb": "EAA-379",
      "RouteUID": "TPE10278",
      "RouteName": "669",
      "Direction": 1,
      "BusPosition": {
        "PositionLat": 25.0605,
        "PositionLon": 121.511383
      },
      "Speed": 13,
      "Azimuth": 354,
      "GPSTime": "2026-05-20T06:54:41+08:00",
      "UpdateTime": "2026-05-20T06:54:55+08:00",
      "source": "TDX Historical Bus RealTimeByFrequency City Taipei",
      "freshness": "fresh",
      "completeness": 1,
      "mode": "tdx-historical",
      "age": "0s",
      "x": "42.27%",
      "y": "46.40%"
    },
    {
      "PlateNumb": "EAL-3198",
      "RouteUID": "TPE10251",
      "RouteName": "南京幹線",
      "Direction": 1,
      "BusPosition": {
        "PositionLat": 25.051295,
        "PositionLon": 121.566122
      },
      "Speed": 37,
      "Azimuth": 89,
      "GPSTime": "2026-05-20T06:54:48+08:00",
      "UpdateTime": "2026-05-20T06:54:55+08:00",
      "source": "TDX Historical Bus RealTimeByFrequency City Taipei",
      "freshness": "fresh",
      "completeness": 1,
      "mode": "tdx-historical",
      "age": "0s",
      "x": "63.77%",
      "y": "49.99%"
    },
    {
      "PlateNumb": "EAL-2085",
      "RouteUID": "TPE10132",
      "RouteName": "234",
      "Direction": 1,
      "BusPosition": {
        "PositionLat": 24.999153,
        "PositionLon": 121.443577
      },
      "Speed": 15,
      "Azimuth": 76,
      "GPSTime": "2026-05-20T06:54:47+08:00",
      "UpdateTime": "2026-05-20T06:54:55+08:00",
      "source": "TDX Historical Bus RealTimeByFrequency City Taipei",
      "freshness": "fresh",
      "completeness": 1,
      "mode": "tdx-historical",
      "age": "0s",
      "x": "15.64%",
      "y": "70.32%"
    },
    {
      "PlateNumb": "EAL-2187",
      "RouteUID": "TPE10142",
      "RouteName": "南環幹線",
      "Direction": 1,
      "BusPosition": {
        "PositionLat": 25.002552,
        "PositionLon": 121.58282
      },
      "Speed": 33,
      "Azimuth": 72,
      "GPSTime": "2026-05-20T06:54:47+08:00",
      "UpdateTime": "2026-05-20T06:54:55+08:00",
      "source": "TDX Historical Bus RealTimeByFrequency City Taipei",
      "freshness": "fresh",
      "completeness": 1,
      "mode": "tdx-historical",
      "age": "0s",
      "x": "70.33%",
      "y": "69.00%"
    },
    {
      "PlateNumb": "EAL-3072",
      "RouteUID": "TPE10241",
      "RouteName": "藍36",
      "Direction": 0,
      "BusPosition": {
        "PositionLat": 25.066805,
        "PositionLon": 121.63666
      },
      "Speed": 0,
      "Azimuth": 47,
      "GPSTime": "2026-05-20T06:54:49+08:00",
      "UpdateTime": "2026-05-20T06:54:55+08:00",
      "source": "TDX Historical Bus RealTimeByFrequency City Taipei",
      "freshness": "fresh",
      "completeness": 1,
      "mode": "tdx-historical",
      "age": "0s",
      "x": "91.47%",
      "y": "43.95%"
    },
    {
      "PlateNumb": "EAA-205",
      "RouteUID": "TPE10232",
      "RouteName": "紅25",
      "Direction": 1,
      "BusPosition": {
        "PositionLat": 25.051142,
        "PositionLon": 121.566975
      },
      "Speed": 0,
      "Azimuth": 0,
      "GPSTime": "2026-05-20T06:54:49+08:00",
      "UpdateTime": "2026-05-20T06:54:55+08:00",
      "source": "TDX Historical Bus RealTimeByFrequency City Taipei",
      "freshness": "fresh",
      "completeness": 1,
      "mode": "tdx-historical",
      "age": "0s",
      "x": "64.10%",
      "y": "50.05%"
    },
    {
      "PlateNumb": "730-FW",
      "RouteUID": "TPE10283",
      "RouteName": "235",
      "Direction": 0,
      "BusPosition": {
        "PositionLat": 25.039633,
        "PositionLon": 121.557563
      },
      "Speed": 21,
      "Azimuth": 183,
      "GPSTime": "2026-05-20T06:54:41+08:00",
      "UpdateTime": "2026-05-20T06:54:55+08:00",
      "source": "TDX Historical Bus RealTimeByFrequency City Taipei",
      "freshness": "fresh",
      "completeness": 1,
      "mode": "tdx-historical",
      "age": "0s",
      "x": "60.41%",
      "y": "54.54%"
    },
    {
      "PlateNumb": "EAL-2061",
      "RouteUID": "TPE10292",
      "RouteName": "藍10",
      "Direction": 1,
      "BusPosition": {
        "PositionLat": 25.051802,
        "PositionLon": 121.563723
      },
      "Speed": 20,
      "Azimuth": 359,
      "GPSTime": "2026-05-20T06:54:41+08:00",
      "UpdateTime": "2026-05-20T06:54:55+08:00",
      "source": "TDX Historical Bus RealTimeByFrequency City Taipei",
      "freshness": "fresh",
      "completeness": 1,
      "mode": "tdx-historical",
      "age": "0s",
      "x": "62.83%",
      "y": "49.80%"
    },
    {
      "PlateNumb": "EAL-1183",
      "RouteUID": "TPE10231",
      "RouteName": "民權幹線",
      "Direction": 1,
      "BusPosition": {
        "PositionLat": 25.059965,
        "PositionLon": 121.51462
      },
      "Speed": 30,
      "Azimuth": 344,
      "GPSTime": "2026-05-20T06:54:49+08:00",
      "UpdateTime": "2026-05-20T06:54:55+08:00",
      "source": "TDX Historical Bus RealTimeByFrequency City Taipei",
      "freshness": "fresh",
      "completeness": 1,
      "mode": "tdx-historical",
      "age": "0s",
      "x": "43.54%",
      "y": "46.61%"
    },
    {
      "PlateNumb": "EAA-090",
      "RouteUID": "TPE10231",
      "RouteName": "民權幹線",
      "Direction": 1,
      "BusPosition": {
        "PositionLat": 25.062705,
        "PositionLon": 121.562998
      },
      "Speed": 39,
      "Azimuth": 83,
      "GPSTime": "2026-05-20T06:54:49+08:00",
      "UpdateTime": "2026-05-20T06:54:55+08:00",
      "source": "TDX Historical Bus RealTimeByFrequency City Taipei",
      "freshness": "fresh",
      "completeness": 1,
      "mode": "tdx-historical",
      "age": "0s",
      "x": "62.54%",
      "y": "45.54%"
    },
    {
      "PlateNumb": "EAL-5151",
      "RouteUID": "TPE10241",
      "RouteName": "藍36",
      "Direction": 1,
      "BusPosition": {
        "PositionLat": 25.065328,
        "PositionLon": 121.634723
      },
      "Speed": 1,
      "Azimuth": 237,
      "GPSTime": "2026-05-20T06:54:46+08:00",
      "UpdateTime": "2026-05-20T06:54:55+08:00",
      "source": "TDX Historical Bus RealTimeByFrequency City Taipei",
      "freshness": "fresh",
      "completeness": 1,
      "mode": "tdx-historical",
      "age": "0s",
      "x": "90.71%",
      "y": "44.52%"
    },
    {
      "PlateNumb": "733-FW",
      "RouteUID": "TPE10283",
      "RouteName": "235",
      "Direction": 0,
      "BusPosition": {
        "PositionLat": 25.0254,
        "PositionLon": 121.424112
      },
      "Speed": 0,
      "Azimuth": 21,
      "GPSTime": "2026-05-20T06:54:48+08:00",
      "UpdateTime": "2026-05-20T06:54:55+08:00",
      "source": "TDX Historical Bus RealTimeByFrequency City Taipei",
      "freshness": "fresh",
      "completeness": 1,
      "mode": "tdx-historical",
      "age": "0s",
      "x": "8.00%",
      "y": "60.09%"
    },
    {
      "PlateNumb": "558-U5",
      "RouteUID": "TPE10181",
      "RouteName": "205",
      "Direction": 1,
      "BusPosition": {
        "PositionLat": 25.034582,
        "PositionLon": 121.501117
      },
      "Speed": 0,
      "Azimuth": 9,
      "GPSTime": "2026-05-20T06:54:46+08:00",
      "UpdateTime": "2026-05-20T06:54:55+08:00",
      "source": "TDX Historical Bus RealTimeByFrequency City Taipei",
      "freshness": "fresh",
      "completeness": 1,
      "mode": "tdx-historical",
      "age": "0s",
      "x": "38.24%",
      "y": "56.51%"
    },
    {
      "PlateNumb": "EAL-1175",
      "RouteUID": "TPE10231",
      "RouteName": "民權幹線",
      "Direction": 0,
      "BusPosition": {
        "PositionLat": 25.062665,
        "PositionLon": 121.526602
      },
      "Speed": 40,
      "Azimuth": 270,
      "GPSTime": "2026-05-20T06:54:47+08:00",
      "UpdateTime": "2026-05-20T06:54:55+08:00",
      "source": "TDX Historical Bus RealTimeByFrequency City Taipei",
      "freshness": "fresh",
      "completeness": 1,
      "mode": "tdx-historical",
      "age": "0s",
      "x": "48.25%",
      "y": "45.56%"
    },
    {
      "PlateNumb": "EAL-5152",
      "RouteUID": "TPE10241",
      "RouteName": "藍36",
      "Direction": 1,
      "BusPosition": {
        "PositionLat": 25.068515,
        "PositionLon": 121.638007
      },
      "Speed": 21,
      "Azimuth": 129,
      "GPSTime": "2026-05-20T06:54:47+08:00",
      "UpdateTime": "2026-05-20T06:54:55+08:00",
      "source": "TDX Historical Bus RealTimeByFrequency City Taipei",
      "freshness": "fresh",
      "completeness": 1,
      "mode": "tdx-historical",
      "age": "0s",
      "x": "92.00%",
      "y": "43.28%"
    },
    {
      "PlateNumb": "365-FZ",
      "RouteUID": "TPE10283",
      "RouteName": "235",
      "Direction": 0,
      "BusPosition": {
        "PositionLat": 25.025285,
        "PositionLon": 121.539352
      },
      "Speed": 35,
      "Azimuth": 99,
      "GPSTime": "2026-05-20T06:54:49+08:00",
      "UpdateTime": "2026-05-20T06:54:55+08:00",
      "source": "TDX Historical Bus RealTimeByFrequency City Taipei",
      "freshness": "fresh",
      "completeness": 1,
      "mode": "tdx-historical",
      "age": "0s",
      "x": "53.26%",
      "y": "60.13%"
    },
    {
      "PlateNumb": "360-FZ",
      "RouteUID": "TPE10283",
      "RouteName": "235",
      "Direction": 0,
      "BusPosition": {
        "PositionLat": 25.01088,
        "PositionLon": 121.427762
      },
      "Speed": 26,
      "Azimuth": 310,
      "GPSTime": "2026-05-20T06:54:47+08:00",
      "UpdateTime": "2026-05-20T06:54:55+08:00",
      "source": "TDX Historical Bus RealTimeByFrequency City Taipei",
      "freshness": "fresh",
      "completeness": 1,
      "mode": "tdx-historical",
      "age": "0s",
      "x": "9.43%",
      "y": "65.75%"
    },
    {
      "PlateNumb": "EAL-3201",
      "RouteUID": "TPE10251",
      "RouteName": "南京幹線",
      "Direction": 1,
      "BusPosition": {
        "PositionLat": 25.051895,
        "PositionLon": 121.53369
      },
      "Speed": 34,
      "Azimuth": 90,
      "GPSTime": "2026-05-20T06:54:47+08:00",
      "UpdateTime": "2026-05-20T06:54:55+08:00",
      "source": "TDX Historical Bus RealTimeByFrequency City Taipei",
      "freshness": "fresh",
      "completeness": 1,
      "mode": "tdx-historical",
      "age": "0s",
      "x": "51.03%",
      "y": "49.76%"
    },
    {
      "PlateNumb": "566-U5",
      "RouteUID": "TPE10181",
      "RouteName": "205",
      "Direction": 0,
      "BusPosition": {
        "PositionLat": 25.046477,
        "PositionLon": 121.516777
      },
      "Speed": 18,
      "Azimuth": 286,
      "GPSTime": "2026-05-20T06:54:46+08:00",
      "UpdateTime": "2026-05-20T06:54:55+08:00",
      "source": "TDX Historical Bus RealTimeByFrequency City Taipei",
      "freshness": "fresh",
      "completeness": 1,
      "mode": "tdx-historical",
      "age": "0s",
      "x": "44.39%",
      "y": "51.87%"
    },
    {
      "PlateNumb": "EAL-3076",
      "RouteUID": "TPE10241",
      "RouteName": "藍36",
      "Direction": 1,
      "BusPosition": {
        "PositionLat": 25.069385,
        "PositionLon": 121.612043
      },
      "Speed": 27,
      "Azimuth": 160,
      "GPSTime": "2026-05-20T06:54:43+08:00",
      "UpdateTime": "2026-05-20T06:54:55+08:00",
      "source": "TDX Historical Bus RealTimeByFrequency City Taipei",
      "freshness": "fresh",
      "completeness": 1,
      "mode": "tdx-historical",
      "age": "0s",
      "x": "81.80%",
      "y": "42.94%"
    },
    {
      "PlateNumb": "732-FW",
      "RouteUID": "TPE10283",
      "RouteName": "235",
      "Direction": 0,
      "BusPosition": {
        "PositionLat": 25.03141,
        "PositionLon": 121.513682
      },
      "Speed": 21,
      "Azimuth": 164,
      "GPSTime": "2026-05-20T06:54:47+08:00",
      "UpdateTime": "2026-05-20T06:54:55+08:00",
      "source": "TDX Historical Bus RealTimeByFrequency City Taipei",
      "freshness": "fresh",
      "completeness": 1,
      "mode": "tdx-historical",
      "age": "0s",
      "x": "43.18%",
      "y": "57.74%"
    },
    {
      "PlateNumb": "EAL-2171",
      "RouteUID": "TPE10283",
      "RouteName": "235",
      "Direction": 0,
      "BusPosition": {
        "PositionLat": 25.043123,
        "PositionLon": 121.502487
      },
      "Speed": 14,
      "Azimuth": 189,
      "GPSTime": "2026-05-20T06:54:48+08:00",
      "UpdateTime": "2026-05-20T06:54:55+08:00",
      "source": "TDX Historical Bus RealTimeByFrequency City Taipei",
      "freshness": "fresh",
      "completeness": 1,
      "mode": "tdx-historical",
      "age": "0s",
      "x": "38.78%",
      "y": "53.18%"
    },
    {
      "PlateNumb": "768-FW",
      "RouteUID": "TPE10221",
      "RouteName": "618",
      "Direction": 0,
      "BusPosition": {
        "PositionLat": 25.062943,
        "PositionLon": 121.515335
      },
      "Speed": 40,
      "Azimuth": 90,
      "GPSTime": "2026-05-20T06:54:47+08:00",
      "UpdateTime": "2026-05-20T06:54:55+08:00",
      "source": "TDX Historical Bus RealTimeByFrequency City Taipei",
      "freshness": "fresh",
      "completeness": 1,
      "mode": "tdx-historical",
      "age": "0s",
      "x": "43.82%",
      "y": "45.45%"
    },
    {
      "PlateNumb": "607-U5",
      "RouteUID": "TPE10293",
      "RouteName": "民生幹線",
      "Direction": 1,
      "BusPosition": {
        "PositionLat": 25.05766,
        "PositionLon": 121.538163
      },
      "Speed": 2,
      "Azimuth": 234,
      "GPSTime": "2026-05-20T06:54:44+08:00",
      "UpdateTime": "2026-05-20T06:54:55+08:00",
      "source": "TDX Historical Bus RealTimeByFrequency City Taipei",
      "freshness": "fresh",
      "completeness": 1,
      "mode": "tdx-historical",
      "age": "0s",
      "x": "52.79%",
      "y": "47.51%"
    },
    {
      "PlateNumb": "EAL-2091",
      "RouteUID": "TPE10132",
      "RouteName": "234",
      "Direction": 0,
      "BusPosition": {
        "PositionLat": 25.035152,
        "PositionLon": 121.5001
      },
      "Speed": 0,
      "Azimuth": 89,
      "GPSTime": "2026-05-20T06:54:42+08:00",
      "UpdateTime": "2026-05-20T06:54:55+08:00",
      "source": "TDX Historical Bus RealTimeByFrequency City Taipei",
      "freshness": "fresh",
      "completeness": 1,
      "mode": "tdx-historical",
      "age": "0s",
      "x": "37.84%",
      "y": "56.29%"
    },
    {
      "PlateNumb": "696-U5",
      "RouteUID": "TPE10293",
      "RouteName": "民生幹線",
      "Direction": 0,
      "BusPosition": {
        "PositionLat": 25.053958,
        "PositionLon": 121.51172
      },
      "Speed": 9,
      "Azimuth": 334,
      "GPSTime": "2026-05-20T06:54:46+08:00",
      "UpdateTime": "2026-05-20T06:54:55+08:00",
      "source": "TDX Historical Bus RealTimeByFrequency City Taipei",
      "freshness": "fresh",
      "completeness": 1,
      "mode": "tdx-historical",
      "age": "0s",
      "x": "42.41%",
      "y": "48.95%"
    },
    {
      "PlateNumb": "EAL-2185",
      "RouteUID": "TPE10142",
      "RouteName": "南環幹線",
      "Direction": 0,
      "BusPosition": {
        "PositionLat": 24.975853,
        "PositionLon": 121.543035
      },
      "Speed": 32,
      "Azimuth": 357,
      "GPSTime": "2026-05-20T06:54:48+08:00",
      "UpdateTime": "2026-05-20T06:54:55+08:00",
      "source": "TDX Historical Bus RealTimeByFrequency City Taipei",
      "freshness": "fresh",
      "completeness": 1,
      "mode": "tdx-historical",
      "age": "0s",
      "x": "54.70%",
      "y": "79.40%"
    },
    {
      "PlateNumb": "EAA-079",
      "RouteUID": "TPE10231",
      "RouteName": "民權幹線",
      "Direction": 0,
      "BusPosition": {
        "PositionLat": 25.062457,
        "PositionLon": 121.533627
      },
      "Speed": 1,
      "Azimuth": 272,
      "GPSTime": "2026-05-20T06:54:46+08:00",
      "UpdateTime": "2026-05-20T06:54:55+08:00",
      "source": "TDX Historical Bus RealTimeByFrequency City Taipei",
      "freshness": "fresh",
      "completeness": 1,
      "mode": "tdx-historical",
      "age": "0s",
      "x": "51.01%",
      "y": "45.64%"
    },
    {
      "PlateNumb": "EAL-5156",
      "RouteUID": "TPE10241",
      "RouteName": "藍36",
      "Direction": 1,
      "BusPosition": {
        "PositionLat": 25.06754,
        "PositionLon": 121.59079
      },
      "Speed": 29,
      "Azimuth": 7,
      "GPSTime": "2026-05-20T06:54:49+08:00",
      "UpdateTime": "2026-05-20T06:54:55+08:00",
      "source": "TDX Historical Bus RealTimeByFrequency City Taipei",
      "freshness": "fresh",
      "completeness": 1,
      "mode": "tdx-historical",
      "age": "0s",
      "x": "73.46%",
      "y": "43.66%"
    },
    {
      "PlateNumb": "EAL-3188",
      "RouteUID": "TPE10251",
      "RouteName": "南京幹線",
      "Direction": 0,
      "BusPosition": {
        "PositionLat": 25.07945,
        "PositionLon": 121.589573
      },
      "Speed": 37,
      "Azimuth": 224,
      "GPSTime": "2026-05-20T06:54:43+08:00",
      "UpdateTime": "2026-05-20T06:54:55+08:00",
      "source": "TDX Historical Bus RealTimeByFrequency City Taipei",
      "freshness": "fresh",
      "completeness": 1,
      "mode": "tdx-historical",
      "age": "0s",
      "x": "72.98%",
      "y": "39.02%"
    },
    {
      "PlateNumb": "EAL-3173",
      "RouteUID": "TPE10251",
      "RouteName": "南京幹線",
      "Direction": 0,
      "BusPosition": {
        "PositionLat": 25.051698,
        "PositionLon": 121.551477
      },
      "Speed": 38,
      "Azimuth": 271,
      "GPSTime": "2026-05-20T06:54:46+08:00",
      "UpdateTime": "2026-05-20T06:54:55+08:00",
      "source": "TDX Historical Bus RealTimeByFrequency City Taipei",
      "freshness": "fresh",
      "completeness": 1,
      "mode": "tdx-historical",
      "age": "0s",
      "x": "58.02%",
      "y": "49.84%"
    },
    {
      "PlateNumb": "EAA-377",
      "RouteUID": "TPE10278",
      "RouteName": "669",
      "Direction": 0,
      "BusPosition": {
        "PositionLat": 25.046245,
        "PositionLon": 121.566717
      },
      "Speed": 6,
      "Azimuth": 158,
      "GPSTime": "2026-05-20T06:54:40+08:00",
      "UpdateTime": "2026-05-20T06:54:55+08:00",
      "source": "TDX Historical Bus RealTimeByFrequency City Taipei",
      "freshness": "fresh",
      "completeness": 1,
      "mode": "tdx-historical",
      "age": "0s",
      "x": "64.00%",
      "y": "51.96%"
    },
    {
      "PlateNumb": "EAL-3792",
      "RouteUID": "TPE10283",
      "RouteName": "235",
      "Direction": 0,
      "BusPosition": {
        "PositionLat": 25.04361,
        "PositionLon": 121.502427
      },
      "Speed": 10,
      "Azimuth": 111,
      "GPSTime": "2026-05-20T06:54:40+08:00",
      "UpdateTime": "2026-05-20T06:54:55+08:00",
      "source": "TDX Historical Bus RealTimeByFrequency City Taipei",
      "freshness": "fresh",
      "completeness": 1,
      "mode": "tdx-historical",
      "age": "0s",
      "x": "38.76%",
      "y": "52.99%"
    },
    {
      "PlateNumb": "EAL-1176",
      "RouteUID": "TPE10231",
      "RouteName": "民權幹線",
      "Direction": 0,
      "BusPosition": {
        "PositionLat": 25.061832,
        "PositionLon": 121.548808
      },
      "Speed": 35,
      "Azimuth": 276,
      "GPSTime": "2026-05-20T06:54:40+08:00",
      "UpdateTime": "2026-05-20T06:54:55+08:00",
      "source": "TDX Historical Bus RealTimeByFrequency City Taipei",
      "freshness": "fresh",
      "completeness": 1,
      "mode": "tdx-historical",
      "age": "0s",
      "x": "56.97%",
      "y": "45.89%"
    },
    {
      "PlateNumb": "737-FW",
      "RouteUID": "TPE10262",
      "RouteName": "2",
      "Direction": 0,
      "BusPosition": {
        "PositionLat": 25.089333,
        "PositionLon": 121.504017
      },
      "Speed": 28,
      "Azimuth": 97,
      "GPSTime": "2026-05-20T06:54:46+08:00",
      "UpdateTime": "2026-05-20T06:54:55+08:00",
      "source": "TDX Historical Bus RealTimeByFrequency City Taipei",
      "freshness": "fresh",
      "completeness": 1,
      "mode": "tdx-historical",
      "age": "0s",
      "x": "39.38%",
      "y": "35.16%"
    },
    {
      "PlateNumb": "EAL-1651",
      "RouteUID": "TPE10232",
      "RouteName": "紅25",
      "Direction": 0,
      "BusPosition": {
        "PositionLat": 25.054672,
        "PositionLon": 121.5767
      },
      "Speed": 0,
      "Azimuth": 240,
      "GPSTime": "2026-05-20T06:54:42+08:00",
      "UpdateTime": "2026-05-20T06:54:55+08:00",
      "source": "TDX Historical Bus RealTimeByFrequency City Taipei",
      "freshness": "fresh",
      "completeness": 1,
      "mode": "tdx-historical",
      "age": "0s",
      "x": "67.92%",
      "y": "48.68%"
    },
    {
      "PlateNumb": "EAL-2172",
      "RouteUID": "TPE10283",
      "RouteName": "235",
      "Direction": 0,
      "BusPosition": {
        "PositionLat": 25.041643,
        "PositionLon": 121.464993
      },
      "Speed": 32,
      "Azimuth": 58,
      "GPSTime": "2026-05-20T06:54:44+08:00",
      "UpdateTime": "2026-05-20T06:54:55+08:00",
      "source": "TDX Historical Bus RealTimeByFrequency City Taipei",
      "freshness": "fresh",
      "completeness": 1,
      "mode": "tdx-historical",
      "age": "0s",
      "x": "24.05%",
      "y": "53.76%"
    },
    {
      "PlateNumb": "EAL-2168",
      "RouteUID": "TPE10283",
      "RouteName": "235",
      "Direction": 0,
      "BusPosition": {
        "PositionLat": 25.035548,
        "PositionLon": 121.449843
      },
      "Speed": 26,
      "Azimuth": 77,
      "GPSTime": "2026-05-20T06:54:46+08:00",
      "UpdateTime": "2026-05-20T06:54:55+08:00",
      "source": "TDX Historical Bus RealTimeByFrequency City Taipei",
      "freshness": "fresh",
      "completeness": 1,
      "mode": "tdx-historical",
      "age": "0s",
      "x": "18.10%",
      "y": "56.13%"
    },
    {
      "PlateNumb": "EAL-2095",
      "RouteUID": "TPE10132",
      "RouteName": "234",
      "Direction": 0,
      "BusPosition": {
        "PositionLat": 25.015357,
        "PositionLon": 121.473048
      },
      "Speed": 34,
      "Azimuth": 62,
      "GPSTime": "2026-05-20T06:54:49+08:00",
      "UpdateTime": "2026-05-20T06:54:55+08:00",
      "source": "TDX Historical Bus RealTimeByFrequency City Taipei",
      "freshness": "fresh",
      "completeness": 1,
      "mode": "tdx-historical",
      "age": "0s",
      "x": "27.22%",
      "y": "64.00%"
    },
    {
      "PlateNumb": "EAL-2196",
      "RouteUID": "TPE10142",
      "RouteName": "南環幹線",
      "Direction": 0,
      "BusPosition": {
        "PositionLat": 24.961492,
        "PositionLon": 121.539062
      },
      "Speed": 0,
      "Azimuth": 15,
      "GPSTime": "2026-05-20T06:54:40+08:00",
      "UpdateTime": "2026-05-20T06:54:55+08:00",
      "source": "TDX Historical Bus RealTimeByFrequency City Taipei",
      "freshness": "fresh",
      "completeness": 1,
      "mode": "tdx-historical",
      "age": "0s",
      "x": "53.14%",
      "y": "85.00%"
    },
    {
      "PlateNumb": "EAL-2193",
      "RouteUID": "TPE10142",
      "RouteName": "南環幹線",
      "Direction": 0,
      "BusPosition": {
        "PositionLat": 24.960203,
        "PositionLon": 121.532507
      },
      "Speed": 4,
      "Azimuth": 188,
      "GPSTime": "2026-05-20T06:54:41+08:00",
      "UpdateTime": "2026-05-20T06:54:55+08:00",
      "source": "TDX Historical Bus RealTimeByFrequency City Taipei",
      "freshness": "fresh",
      "completeness": 1,
      "mode": "tdx-historical",
      "age": "0s",
      "x": "50.57%",
      "y": "85.50%"
    },
    {
      "PlateNumb": "EAL-2189",
      "RouteUID": "TPE10142",
      "RouteName": "南環幹線",
      "Direction": 0,
      "BusPosition": {
        "PositionLat": 24.96127,
        "PositionLon": 121.529643
      },
      "Speed": 35,
      "Azimuth": 112,
      "GPSTime": "2026-05-20T06:54:46+08:00",
      "UpdateTime": "2026-05-20T06:54:55+08:00",
      "source": "TDX Historical Bus RealTimeByFrequency City Taipei",
      "freshness": "fresh",
      "completeness": 1,
      "mode": "tdx-historical",
      "age": "0s",
      "x": "49.44%",
      "y": "85.09%"
    },
    {
      "PlateNumb": "685-U5",
      "RouteUID": "TPE10282",
      "RouteName": "663",
      "Direction": 0,
      "BusPosition": {
        "PositionLat": 25.041997,
        "PositionLon": 121.465678
      },
      "Speed": 32,
      "Azimuth": 56,
      "GPSTime": "2026-05-20T06:54:44+08:00",
      "UpdateTime": "2026-05-20T06:54:55+08:00",
      "source": "TDX Historical Bus RealTimeByFrequency City Taipei",
      "freshness": "fresh",
      "completeness": 1,
      "mode": "tdx-historical",
      "age": "0s",
      "x": "24.32%",
      "y": "53.62%"
    },
    {
      "PlateNumb": "EAL-5155",
      "RouteUID": "TPE10241",
      "RouteName": "藍36",
      "Direction": 0,
      "BusPosition": {
        "PositionLat": 25.070687,
        "PositionLon": 121.61102
      },
      "Speed": 35,
      "Azimuth": 308,
      "GPSTime": "2026-05-20T06:54:44+08:00",
      "UpdateTime": "2026-05-20T06:54:55+08:00",
      "source": "TDX Historical Bus RealTimeByFrequency City Taipei",
      "freshness": "fresh",
      "completeness": 1,
      "mode": "tdx-historical",
      "age": "0s",
      "x": "81.40%",
      "y": "42.43%"
    },
    {
      "PlateNumb": "KKA-2530",
      "RouteUID": "TPE10293",
      "RouteName": "民生幹線",
      "Direction": 0,
      "BusPosition": {
        "PositionLat": 25.057718,
        "PositionLon": 121.549557
      },
      "Speed": 0,
      "Azimuth": 253,
      "GPSTime": "2026-05-20T06:54:45+08:00",
      "UpdateTime": "2026-05-20T06:54:55+08:00",
      "source": "TDX Historical Bus RealTimeByFrequency City Taipei",
      "freshness": "fresh",
      "completeness": 1,
      "mode": "tdx-historical",
      "age": "0s",
      "x": "57.26%",
      "y": "47.49%"
    },
    {
      "PlateNumb": "EAL-1182",
      "RouteUID": "TPE10231",
      "RouteName": "民權幹線",
      "Direction": 0,
      "BusPosition": {
        "PositionLat": 25.058742,
        "PositionLon": 121.61422
      },
      "Speed": 0,
      "Azimuth": 1,
      "GPSTime": "2026-05-20T06:54:43+08:00",
      "UpdateTime": "2026-05-20T06:54:55+08:00",
      "source": "TDX Historical Bus RealTimeByFrequency City Taipei",
      "freshness": "fresh",
      "completeness": 1,
      "mode": "tdx-historical",
      "age": "0s",
      "x": "82.66%",
      "y": "47.09%"
    },
    {
      "PlateNumb": "EAL-3185",
      "RouteUID": "TPE10232",
      "RouteName": "紅25",
      "Direction": 1,
      "BusPosition": {
        "PositionLat": 25.05797,
        "PositionLon": 121.605905
      },
      "Speed": 35,
      "Azimuth": 79,
      "GPSTime": "2026-05-20T06:54:47+08:00",
      "UpdateTime": "2026-05-20T06:54:55+08:00",
      "source": "TDX Historical Bus RealTimeByFrequency City Taipei",
      "freshness": "fresh",
      "completeness": 1,
      "mode": "tdx-historical",
      "age": "0s",
      "x": "79.39%",
      "y": "47.39%"
    },
    {
      "PlateNumb": "758-FW",
      "RouteUID": "TPE10263",
      "RouteName": "536",
      "Direction": 0,
      "BusPosition": {
        "PositionLat": 25.089678,
        "PositionLon": 121.502747
      },
      "Speed": 5,
      "Azimuth": 117,
      "GPSTime": "2026-05-20T06:54:41+08:00",
      "UpdateTime": "2026-05-20T06:54:55+08:00",
      "source": "TDX Historical Bus RealTimeByFrequency City Taipei",
      "freshness": "fresh",
      "completeness": 1,
      "mode": "tdx-historical",
      "age": "0s",
      "x": "38.88%",
      "y": "35.03%"
    },
    {
      "PlateNumb": "565-U5",
      "RouteUID": "TPE10181",
      "RouteName": "205",
      "Direction": 0,
      "BusPosition": {
        "PositionLat": 25.054475,
        "PositionLon": 121.607493
      },
      "Speed": 45,
      "Azimuth": 258,
      "GPSTime": "2026-05-20T06:54:49+08:00",
      "UpdateTime": "2026-05-20T06:54:55+08:00",
      "source": "TDX Historical Bus RealTimeByFrequency City Taipei",
      "freshness": "fresh",
      "completeness": 1,
      "mode": "tdx-historical",
      "age": "0s",
      "x": "80.02%",
      "y": "48.75%"
    },
    {
      "PlateNumb": "557-U5",
      "RouteUID": "TPE10181",
      "RouteName": "205",
      "Direction": 0,
      "BusPosition": {
        "PositionLat": 25.042435,
        "PositionLon": 121.617
      },
      "Speed": 20,
      "Azimuth": 21,
      "GPSTime": "2026-05-20T06:54:42+08:00",
      "UpdateTime": "2026-05-20T06:54:55+08:00",
      "source": "TDX Historical Bus RealTimeByFrequency City Taipei",
      "freshness": "fresh",
      "completeness": 1,
      "mode": "tdx-historical",
      "age": "0s",
      "x": "83.75%",
      "y": "53.45%"
    },
    {
      "PlateNumb": "EAA-089",
      "RouteUID": "TPE10231",
      "RouteName": "民權幹線",
      "Direction": 0,
      "BusPosition": {
        "PositionLat": 25.071893,
        "PositionLon": 121.609212
      },
      "Speed": 0,
      "Azimuth": 317,
      "GPSTime": "2026-05-20T06:54:48+08:00",
      "UpdateTime": "2026-05-20T06:54:55+08:00",
      "source": "TDX Historical Bus RealTimeByFrequency City Taipei",
      "freshness": "fresh",
      "completeness": 1,
      "mode": "tdx-historical",
      "age": "0s",
      "x": "80.69%",
      "y": "41.96%"
    },
    {
      "PlateNumb": "EAL-3182",
      "RouteUID": "TPE10251",
      "RouteName": "南京幹線",
      "Direction": 0,
      "BusPosition": {
        "PositionLat": 25.072405,
        "PositionLon": 121.608105
      },
      "Speed": 27,
      "Azimuth": 290,
      "GPSTime": "2026-05-20T06:54:49+08:00",
      "UpdateTime": "2026-05-20T06:54:55+08:00",
      "source": "TDX Historical Bus RealTimeByFrequency City Taipei",
      "freshness": "fresh",
      "completeness": 1,
      "mode": "tdx-historical",
      "age": "0s",
      "x": "80.26%",
      "y": "41.76%"
    },
    {
      "PlateNumb": "EAL-1650",
      "RouteUID": "TPE10241",
      "RouteName": "藍36",
      "Direction": 0,
      "BusPosition": {
        "PositionLat": 25.070123,
        "PositionLon": 121.611782
      },
      "Speed": 16,
      "Azimuth": 328,
      "GPSTime": "2026-05-20T06:54:42+08:00",
      "UpdateTime": "2026-05-20T06:54:55+08:00",
      "source": "TDX Historical Bus RealTimeByFrequency City Taipei",
      "freshness": "fresh",
      "completeness": 1,
      "mode": "tdx-historical",
      "age": "0s",
      "x": "81.70%",
      "y": "42.65%"
    },
    {
      "PlateNumb": "EAL-2195",
      "RouteUID": "TPE10142",
      "RouteName": "南環幹線",
      "Direction": 0,
      "BusPosition": {
        "PositionLat": 24.978933,
        "PositionLon": 121.545078
      },
      "Speed": 39,
      "Azimuth": 148,
      "GPSTime": "2026-05-20T06:54:45+08:00",
      "UpdateTime": "2026-05-20T06:54:55+08:00",
      "source": "TDX Historical Bus RealTimeByFrequency City Taipei",
      "freshness": "fresh",
      "completeness": 1,
      "mode": "tdx-historical",
      "age": "0s",
      "x": "55.51%",
      "y": "78.20%"
    },
    {
      "PlateNumb": "EAL-2198",
      "RouteUID": "TPE10142",
      "RouteName": "南環幹線",
      "Direction": 0,
      "BusPosition": {
        "PositionLat": 24.958932,
        "PositionLon": 121.509325
      },
      "Speed": 13,
      "Azimuth": 94,
      "GPSTime": "2026-05-20T06:54:41+08:00",
      "UpdateTime": "2026-05-20T06:54:55+08:00",
      "source": "TDX Historical Bus RealTimeByFrequency City Taipei",
      "freshness": "fresh",
      "completeness": 1,
      "mode": "tdx-historical",
      "age": "0s",
      "x": "41.46%",
      "y": "86.00%"
    },
    {
      "PlateNumb": "690-U5",
      "RouteUID": "TPE10293",
      "RouteName": "民生幹線",
      "Direction": 0,
      "BusPosition": {
        "PositionLat": 25.061362,
        "PositionLon": 121.582008
      },
      "Speed": 15,
      "Azimuth": 153,
      "GPSTime": "2026-05-20T06:54:43+08:00",
      "UpdateTime": "2026-05-20T06:54:55+08:00",
      "source": "TDX Historical Bus RealTimeByFrequency City Taipei",
      "freshness": "fresh",
      "completeness": 1,
      "mode": "tdx-historical",
      "age": "0s",
      "x": "70.01%",
      "y": "46.07%"
    },
    {
      "PlateNumb": "688-U5",
      "RouteUID": "TPE10293",
      "RouteName": "民生幹線",
      "Direction": 0,
      "BusPosition": {
        "PositionLat": 25.058868,
        "PositionLon": 121.580245
      },
      "Speed": 15,
      "Azimuth": 73,
      "GPSTime": "2026-05-20T06:54:43+08:00",
      "UpdateTime": "2026-05-20T06:54:55+08:00",
      "source": "TDX Historical Bus RealTimeByFrequency City Taipei",
      "freshness": "fresh",
      "completeness": 1,
      "mode": "tdx-historical",
      "age": "0s",
      "x": "69.32%",
      "y": "47.04%"
    },
    {
      "PlateNumb": "EAL-2096",
      "RouteUID": "TPE10132",
      "RouteName": "234",
      "Direction": 0,
      "BusPosition": {
        "PositionLat": 25.005268,
        "PositionLon": 121.447193
      },
      "Speed": 50,
      "Azimuth": 191,
      "GPSTime": "2026-05-20T06:54:40+08:00",
      "UpdateTime": "2026-05-20T06:54:55+08:00",
      "source": "TDX Historical Bus RealTimeByFrequency City Taipei",
      "freshness": "fresh",
      "completeness": 1,
      "mode": "tdx-historical",
      "age": "0s",
      "x": "17.06%",
      "y": "67.94%"
    },
    {
      "PlateNumb": "EAL-1185",
      "RouteUID": "TPE10231",
      "RouteName": "民權幹線",
      "Direction": 0,
      "BusPosition": {
        "PositionLat": 25.057688,
        "PositionLon": 121.60309
      },
      "Speed": 40,
      "Azimuth": 89,
      "GPSTime": "2026-05-20T06:54:49+08:00",
      "UpdateTime": "2026-05-20T06:54:55+08:00",
      "source": "TDX Historical Bus RealTimeByFrequency City Taipei",
      "freshness": "fresh",
      "completeness": 1,
      "mode": "tdx-historical",
      "age": "0s",
      "x": "78.29%",
      "y": "47.50%"
    },
    {
      "PlateNumb": "682-U5",
      "RouteUID": "TPE10283",
      "RouteName": "235",
      "Direction": 1,
      "BusPosition": {
        "PositionLat": 24.99517,
        "PositionLon": 121.439495
      },
      "Speed": 0,
      "Azimuth": 0,
      "GPSTime": "2026-05-20T06:54:47+08:00",
      "UpdateTime": "2026-05-20T06:54:55+08:00",
      "source": "TDX Historical Bus RealTimeByFrequency City Taipei",
      "freshness": "fresh",
      "completeness": 1,
      "mode": "tdx-historical",
      "age": "0s",
      "x": "14.04%",
      "y": "71.87%"
    },
    {
      "PlateNumb": "KKA-2529",
      "RouteUID": "TPE10293",
      "RouteName": "民生幹線",
      "Direction": 0,
      "BusPosition": {
        "PositionLat": 25.064797,
        "PositionLon": 121.579177
      },
      "Speed": 20,
      "Azimuth": 231,
      "GPSTime": "2026-05-20T06:54:47+08:00",
      "UpdateTime": "2026-05-20T06:54:55+08:00",
      "source": "TDX Historical Bus RealTimeByFrequency City Taipei",
      "freshness": "fresh",
      "completeness": 1,
      "mode": "tdx-historical",
      "age": "0s",
      "x": "68.90%",
      "y": "44.73%"
    },
    {
      "PlateNumb": "366-FZ",
      "RouteUID": "TPE10283",
      "RouteName": "235",
      "Direction": 1,
      "BusPosition": {
        "PositionLat": 24.994727,
        "PositionLon": 121.44466
      },
      "Speed": 0,
      "Azimuth": 350,
      "GPSTime": "2026-05-20T06:54:42+08:00",
      "UpdateTime": "2026-05-20T06:54:55+08:00",
      "source": "TDX Historical Bus RealTimeByFrequency City Taipei",
      "freshness": "fresh",
      "completeness": 1,
      "mode": "tdx-historical",
      "age": "0s",
      "x": "16.07%",
      "y": "72.05%"
    },
    {
      "PlateNumb": "550-U5",
      "RouteUID": "TPE10181",
      "RouteName": "205",
      "Direction": 0,
      "BusPosition": {
        "PositionLat": 25.026497,
        "PositionLon": 121.507248
      },
      "Speed": 3,
      "Azimuth": 33,
      "GPSTime": "2026-05-20T06:54:32+08:00",
      "UpdateTime": "2026-05-20T06:54:45+08:00",
      "source": "TDX Historical Bus RealTimeByFrequency City Taipei",
      "freshness": "fresh",
      "completeness": 1,
      "mode": "tdx-historical",
      "age": "0s",
      "x": "40.65%",
      "y": "59.66%"
    },
    {
      "PlateNumb": "KKC-1281",
      "RouteUID": "TPE10272",
      "RouteName": "303",
      "Direction": 1,
      "BusPosition": {
        "PositionLat": 25.096313,
        "PositionLon": 121.530568
      },
      "Speed": 32,
      "Azimuth": 259,
      "GPSTime": "2026-05-20T06:54:37+08:00",
      "UpdateTime": "2026-05-20T06:54:45+08:00",
      "source": "TDX Historical Bus RealTimeByFrequency City Taipei",
      "freshness": "fresh",
      "completeness": 1,
      "mode": "tdx-historical",
      "age": "0s",
      "x": "49.81%",
      "y": "32.44%"
    },
    {
      "PlateNumb": "361-FZ",
      "RouteUID": "TPE10283",
      "RouteName": "235",
      "Direction": 0,
      "BusPosition": {
        "PositionLat": 25.040345,
        "PositionLon": 121.549148
      },
      "Speed": 20,
      "Azimuth": 351,
      "GPSTime": "2026-05-20T06:54:32+08:00",
      "UpdateTime": "2026-05-20T06:54:45+08:00",
      "source": "TDX Historical Bus RealTimeByFrequency City Taipei",
      "freshness": "fresh",
      "completeness": 1,
      "mode": "tdx-historical",
      "age": "0s",
      "x": "57.10%",
      "y": "54.26%"
    },
    {
      "PlateNumb": "EAL-2088",
      "RouteUID": "TPE10132",
      "RouteName": "234",
      "Direction": 1,
      "BusPosition": {
        "PositionLat": 25.012038,
        "PositionLon": 121.444813
      },
      "Speed": 0,
      "Azimuth": 127,
      "GPSTime": "2026-05-20T06:54:36+08:00",
      "UpdateTime": "2026-05-20T06:54:45+08:00",
      "source": "TDX Historical Bus RealTimeByFrequency City Taipei",
      "freshness": "fresh",
      "completeness": 1,
      "mode": "tdx-historical",
      "age": "0s",
      "x": "16.13%",
      "y": "65.30%"
    },
    {
      "PlateNumb": "EAL-3177",
      "RouteUID": "TPE10251",
      "RouteName": "南京幹線",
      "Direction": 1,
      "BusPosition": {
        "PositionLat": 25.057685,
        "PositionLon": 121.597392
      },
      "Speed": 0,
      "Azimuth": 152,
      "GPSTime": "2026-05-20T06:54:32+08:00",
      "UpdateTime": "2026-05-20T06:54:45+08:00",
      "source": "TDX Historical Bus RealTimeByFrequency City Taipei",
      "freshness": "fresh",
      "completeness": 1,
      "mode": "tdx-historical",
      "age": "0s",
      "x": "76.05%",
      "y": "47.50%"
    },
    {
      "PlateNumb": "739-FW",
      "RouteUID": "TPE10263",
      "RouteName": "536",
      "Direction": 1,
      "BusPosition": {
        "PositionLat": 25.095415,
        "PositionLon": 121.524508
      },
      "Speed": 0,
      "Azimuth": 166,
      "GPSTime": "2026-05-20T06:54:37+08:00",
      "UpdateTime": "2026-05-20T06:54:45+08:00",
      "source": "TDX Historical Bus RealTimeByFrequency City Taipei",
      "freshness": "fresh",
      "completeness": 1,
      "mode": "tdx-historical",
      "age": "0s",
      "x": "47.43%",
      "y": "32.79%"
    },
    {
      "PlateNumb": "EAL-3073",
      "RouteUID": "TPE10241",
      "RouteName": "藍36",
      "Direction": 1,
      "BusPosition": {
        "PositionLat": 25.068807,
        "PositionLon": 121.613972
      },
      "Speed": 18,
      "Azimuth": 95,
      "GPSTime": "2026-05-20T06:54:39+08:00",
      "UpdateTime": "2026-05-20T06:54:45+08:00",
      "source": "TDX Historical Bus RealTimeByFrequency City Taipei",
      "freshness": "fresh",
      "completeness": 1,
      "mode": "tdx-historical",
      "age": "0s",
      "x": "82.56%",
      "y": "43.17%"
    },
    {
      "PlateNumb": "EAL-2069",
      "RouteUID": "TPE10292",
      "RouteName": "藍10",
      "Direction": 1,
      "BusPosition": {
        "PositionLat": 25.061947,
        "PositionLon": 121.582515
      },
      "Speed": 0,
      "Azimuth": 249,
      "GPSTime": "2026-05-20T06:54:39+08:00",
      "UpdateTime": "2026-05-20T06:54:45+08:00",
      "source": "TDX Historical Bus RealTimeByFrequency City Taipei",
      "freshness": "fresh",
      "completeness": 1,
      "mode": "tdx-historical",
      "age": "0s",
      "x": "70.21%",
      "y": "45.84%"
    },
    {
      "PlateNumb": "EAL-2188",
      "RouteUID": "TPE10142",
      "RouteName": "南環幹線",
      "Direction": 1,
      "BusPosition": {
        "PositionLat": 25.032895,
        "PositionLon": 121.568207
      },
      "Speed": 11,
      "Azimuth": 175,
      "GPSTime": "2026-05-20T06:54:38+08:00",
      "UpdateTime": "2026-05-20T06:54:45+08:00",
      "source": "TDX Historical Bus RealTimeByFrequency City Taipei",
      "freshness": "fresh",
      "completeness": 1,
      "mode": "tdx-historical",
      "age": "0s",
      "x": "64.59%",
      "y": "57.17%"
    },
    {
      "PlateNumb": "731-FW",
      "RouteUID": "TPE10283",
      "RouteName": "235",
      "Direction": 1,
      "BusPosition": {
        "PositionLat": 25.034577,
        "PositionLon": 121.515205
      },
      "Speed": 0,
      "Azimuth": 34,
      "GPSTime": "2026-05-20T06:54:34+08:00",
      "UpdateTime": "2026-05-20T06:54:45+08:00",
      "source": "TDX Historical Bus RealTimeByFrequency City Taipei",
      "freshness": "fresh",
      "completeness": 1,
      "mode": "tdx-historical",
      "age": "0s",
      "x": "43.77%",
      "y": "56.51%"
    },
    {
      "PlateNumb": "359-FZ",
      "RouteUID": "TPE10283",
      "RouteName": "235",
      "Direction": 1,
      "BusPosition": {
        "PositionLat": 25.033412,
        "PositionLon": 121.552662
      },
      "Speed": 12,
      "Azimuth": 128,
      "GPSTime": "2026-05-20T06:54:38+08:00",
      "UpdateTime": "2026-05-20T06:54:45+08:00",
      "source": "TDX Historical Bus RealTimeByFrequency City Taipei",
      "freshness": "fresh",
      "completeness": 1,
      "mode": "tdx-historical",
      "age": "0s",
      "x": "58.48%",
      "y": "56.96%"
    },
    {
      "PlateNumb": "EAL-2087",
      "RouteUID": "TPE10132",
      "RouteName": "234",
      "Direction": 1,
      "BusPosition": {
        "PositionLat": 25.013403,
        "PositionLon": 121.462253
      },
      "Speed": 1,
      "Azimuth": 34,
      "GPSTime": "2026-05-20T06:54:37+08:00",
      "UpdateTime": "2026-05-20T06:54:45+08:00",
      "source": "TDX Historical Bus RealTimeByFrequency City Taipei",
      "freshness": "fresh",
      "completeness": 1,
      "mode": "tdx-historical",
      "age": "0s",
      "x": "22.98%",
      "y": "64.76%"
    },
    {
      "PlateNumb": "EAA-037",
      "RouteUID": "TPE10231",
      "RouteName": "民權幹線",
      "Direction": 1,
      "BusPosition": {
        "PositionLat": 25.066575,
        "PositionLon": 121.578203
      },
      "Speed": 0,
      "Azimuth": 72,
      "GPSTime": "2026-05-20T06:54:33+08:00",
      "UpdateTime": "2026-05-20T06:54:45+08:00",
      "source": "TDX Historical Bus RealTimeByFrequency City Taipei",
      "freshness": "fresh",
      "completeness": 1,
      "mode": "tdx-historical",
      "age": "0s",
      "x": "68.51%",
      "y": "44.04%"
    },
    {
      "PlateNumb": "EAL-2197",
      "RouteUID": "TPE10142",
      "RouteName": "南環幹線",
      "Direction": 0,
      "BusPosition": {
        "PositionLat": 25.039055,
        "PositionLon": 121.56573
      },
      "Speed": 6,
      "Azimuth": 89,
      "GPSTime": "2026-05-20T06:54:35+08:00",
      "UpdateTime": "2026-05-20T06:54:45+08:00",
      "source": "TDX Historical Bus RealTimeByFrequency City Taipei",
      "freshness": "fresh",
      "completeness": 1,
      "mode": "tdx-historical",
      "age": "0s",
      "x": "63.62%",
      "y": "54.76%"
    },
    {
      "PlateNumb": "767-FW",
      "RouteUID": "TPE10221",
      "RouteName": "618",
      "Direction": 0,
      "BusPosition": {
        "PositionLat": 25.052518,
        "PositionLon": 121.466012
      },
      "Speed": 28,
      "Azimuth": 8,
      "GPSTime": "2026-05-20T06:54:39+08:00",
      "UpdateTime": "2026-05-20T06:54:45+08:00",
      "source": "TDX Historical Bus RealTimeByFrequency City Taipei",
      "freshness": "fresh",
      "completeness": 1,
      "mode": "tdx-historical",
      "age": "0s",
      "x": "24.45%",
      "y": "49.52%"
    },
    {
      "PlateNumb": "EAL-2180",
      "RouteUID": "TPE10142",
      "RouteName": "南環幹線",
      "Direction": 0,
      "BusPosition": {
        "PositionLat": 25.035638,
        "PositionLon": 121.563573
      },
      "Speed": 0,
      "Azimuth": 356,
      "GPSTime": "2026-05-20T06:54:30+08:00",
      "UpdateTime": "2026-05-20T06:54:45+08:00",
      "source": "TDX Historical Bus RealTimeByFrequency City Taipei",
      "freshness": "fresh",
      "completeness": 1,
      "mode": "tdx-historical",
      "age": "0s",
      "x": "62.77%",
      "y": "56.10%"
    },
    {
      "PlateNumb": "EAL-2090",
      "RouteUID": "TPE10132",
      "RouteName": "234",
      "Direction": 1,
      "BusPosition": {
        "PositionLat": 25.012703,
        "PositionLon": 121.467328
      },
      "Speed": 43,
      "Azimuth": 243,
      "GPSTime": "2026-05-20T06:54:34+08:00",
      "UpdateTime": "2026-05-20T06:54:45+08:00",
      "source": "TDX Historical Bus RealTimeByFrequency City Taipei",
      "freshness": "fresh",
      "completeness": 1,
      "mode": "tdx-historical",
      "age": "0s",
      "x": "24.97%",
      "y": "65.04%"
    },
    {
      "PlateNumb": "363-FZ",
      "RouteUID": "TPE10283",
      "RouteName": "235",
      "Direction": 0,
      "BusPosition": {
        "PositionLat": 25.029897,
        "PositionLon": 121.515633
      },
      "Speed": 9,
      "Azimuth": 78,
      "GPSTime": "2026-05-20T06:54:35+08:00",
      "UpdateTime": "2026-05-20T06:54:45+08:00",
      "source": "TDX Historical Bus RealTimeByFrequency City Taipei",
      "freshness": "fresh",
      "completeness": 1,
      "mode": "tdx-historical",
      "age": "0s",
      "x": "43.94%",
      "y": "58.33%"
    },
    {
      "PlateNumb": "EAL-2081",
      "RouteUID": "TPE10132",
      "RouteName": "234",
      "Direction": 1,
      "BusPosition": {
        "PositionLat": 25.025585,
        "PositionLon": 121.492153
      },
      "Speed": 43,
      "Azimuth": 226,
      "GPSTime": "2026-05-20T06:54:30+08:00",
      "UpdateTime": "2026-05-20T06:54:45+08:00",
      "source": "TDX Historical Bus RealTimeByFrequency City Taipei",
      "freshness": "fresh",
      "completeness": 1,
      "mode": "tdx-historical",
      "age": "0s",
      "x": "34.72%",
      "y": "60.02%"
    },
    {
      "PlateNumb": "EAL-2199",
      "RouteUID": "TPE10142",
      "RouteName": "南環幹線",
      "Direction": 0,
      "BusPosition": {
        "PositionLat": 24.987833,
        "PositionLon": 121.574762
      },
      "Speed": 0,
      "Azimuth": 270,
      "GPSTime": "2026-05-20T06:54:38+08:00",
      "UpdateTime": "2026-05-20T06:54:45+08:00",
      "source": "TDX Historical Bus RealTimeByFrequency City Taipei",
      "freshness": "fresh",
      "completeness": 1,
      "mode": "tdx-historical",
      "age": "0s",
      "x": "67.16%",
      "y": "74.73%"
    },
    {
      "PlateNumb": "738-FW",
      "RouteUID": "TPE10293",
      "RouteName": "民生幹線",
      "Direction": 1,
      "BusPosition": {
        "PositionLat": 25.054705,
        "PositionLon": 121.569663
      },
      "Speed": 0,
      "Azimuth": 175,
      "GPSTime": "2026-05-20T06:54:33+08:00",
      "UpdateTime": "2026-05-20T06:54:45+08:00",
      "source": "TDX Historical Bus RealTimeByFrequency City Taipei",
      "freshness": "fresh",
      "completeness": 1,
      "mode": "tdx-historical",
      "age": "0s",
      "x": "65.16%",
      "y": "48.66%"
    },
    {
      "PlateNumb": "EAL-2182",
      "RouteUID": "TPE10142",
      "RouteName": "南環幹線",
      "Direction": 0,
      "BusPosition": {
        "PositionLat": 24.982508,
        "PositionLon": 121.564508
      },
      "Speed": 15,
      "Azimuth": 76,
      "GPSTime": "2026-05-20T06:54:39+08:00",
      "UpdateTime": "2026-05-20T06:54:45+08:00",
      "source": "TDX Historical Bus RealTimeByFrequency City Taipei",
      "freshness": "fresh",
      "completeness": 1,
      "mode": "tdx-historical",
      "age": "0s",
      "x": "63.14%",
      "y": "76.81%"
    },
    {
      "PlateNumb": "EAL-2083",
      "RouteUID": "TPE10132",
      "RouteName": "234",
      "Direction": 1,
      "BusPosition": {
        "PositionLat": 25.035532,
        "PositionLon": 121.499303
      },
      "Speed": 0,
      "Azimuth": 171,
      "GPSTime": "2026-05-20T06:54:30+08:00",
      "UpdateTime": "2026-05-20T06:54:45+08:00",
      "source": "TDX Historical Bus RealTimeByFrequency City Taipei",
      "freshness": "fresh",
      "completeness": 1,
      "mode": "tdx-historical",
      "age": "0s",
      "x": "37.53%",
      "y": "56.14%"
    },
    {
      "PlateNumb": "EAA-036",
      "RouteUID": "TPE10231",
      "RouteName": "民權幹線",
      "Direction": 1,
      "BusPosition": {
        "PositionLat": 25.062682,
        "PositionLon": 121.525483
      },
      "Speed": 0,
      "Azimuth": 91,
      "GPSTime": "2026-05-20T06:54:34+08:00",
      "UpdateTime": "2026-05-20T06:54:45+08:00",
      "source": "TDX Historical Bus RealTimeByFrequency City Taipei",
      "freshness": "fresh",
      "completeness": 1,
      "mode": "tdx-historical",
      "age": "0s",
      "x": "47.81%",
      "y": "45.55%"
    },
    {
      "PlateNumb": "EAL-3080",
      "RouteUID": "TPE10241",
      "RouteName": "藍36",
      "Direction": 1,
      "BusPosition": {
        "PositionLat": 25.066867,
        "PositionLon": 121.624327
      },
      "Speed": 34,
      "Azimuth": 84,
      "GPSTime": "2026-05-20T06:54:39+08:00",
      "UpdateTime": "2026-05-20T06:54:45+08:00",
      "source": "TDX Historical Bus RealTimeByFrequency City Taipei",
      "freshness": "fresh",
      "completeness": 1,
      "mode": "tdx-historical",
      "age": "0s",
      "x": "86.63%",
      "y": "43.92%"
    },
    {
      "PlateNumb": "EAL-2086",
      "RouteUID": "TPE10132",
      "RouteName": "234",
      "Direction": 0,
      "BusPosition": {
        "PositionLat": 25.011285,
        "PositionLon": 121.464342
      },
      "Speed": 4,
      "Azimuth": 62,
      "GPSTime": "2026-05-20T06:54:37+08:00",
      "UpdateTime": "2026-05-20T06:54:45+08:00",
      "source": "TDX Historical Bus RealTimeByFrequency City Taipei",
      "freshness": "fresh",
      "completeness": 1,
      "mode": "tdx-historical",
      "age": "0s",
      "x": "23.80%",
      "y": "65.59%"
    },
    {
      "PlateNumb": "EAL-2169",
      "RouteUID": "TPE10283",
      "RouteName": "235",
      "Direction": 0,
      "BusPosition": {
        "PositionLat": 25.031468,
        "PositionLon": 121.513685
      },
      "Speed": 21,
      "Azimuth": 167,
      "GPSTime": "2026-05-20T06:54:31+08:00",
      "UpdateTime": "2026-05-20T06:54:45+08:00",
      "source": "TDX Historical Bus RealTimeByFrequency City Taipei",
      "freshness": "fresh",
      "completeness": 1,
      "mode": "tdx-historical",
      "age": "0s",
      "x": "43.18%",
      "y": "57.72%"
    },
    {
      "PlateNumb": "EAL-5150",
      "RouteUID": "TPE10241",
      "RouteName": "藍36",
      "Direction": 1,
      "BusPosition": {
        "PositionLat": 25.060553,
        "PositionLon": 121.591465
      },
      "Speed": 35,
      "Azimuth": 342,
      "GPSTime": "2026-05-20T06:54:30+08:00",
      "UpdateTime": "2026-05-20T06:54:45+08:00",
      "source": "TDX Historical Bus RealTimeByFrequency City Taipei",
      "freshness": "fresh",
      "completeness": 1,
      "mode": "tdx-historical",
      "age": "0s",
      "x": "73.72%",
      "y": "46.38%"
    },
    {
      "PlateNumb": "EAL-1655",
      "RouteUID": "TPE10241",
      "RouteName": "藍36",
      "Direction": 0,
      "BusPosition": {
        "PositionLat": 25.068885,
        "PositionLon": 121.593068
      },
      "Speed": 0,
      "Azimuth": 0,
      "GPSTime": "2026-05-20T06:54:30+08:00",
      "UpdateTime": "2026-05-20T06:54:45+08:00",
      "source": "TDX Historical Bus RealTimeByFrequency City Taipei",
      "freshness": "fresh",
      "completeness": 1,
      "mode": "tdx-historical",
      "age": "0s",
      "x": "74.35%",
      "y": "43.14%"
    },
    {
      "PlateNumb": "EAA-206",
      "RouteUID": "TPE10232",
      "RouteName": "紅25",
      "Direction": 0,
      "BusPosition": {
        "PositionLat": 25.052842,
        "PositionLon": 121.519505
      },
      "Speed": 20,
      "Azimuth": 279,
      "GPSTime": "2026-05-20T06:54:35+08:00",
      "UpdateTime": "2026-05-20T06:54:45+08:00",
      "source": "TDX Historical Bus RealTimeByFrequency City Taipei",
      "freshness": "fresh",
      "completeness": 1,
      "mode": "tdx-historical",
      "age": "0s",
      "x": "45.46%",
      "y": "49.39%"
    },
    {
      "PlateNumb": "555-U5",
      "RouteUID": "TPE10181",
      "RouteName": "205",
      "Direction": 0,
      "BusPosition": {
        "PositionLat": 25.048438,
        "PositionLon": 121.56125
      },
      "Speed": 22,
      "Azimuth": 244,
      "GPSTime": "2026-05-20T06:54:30+08:00",
      "UpdateTime": "2026-05-20T06:54:45+08:00",
      "source": "TDX Historical Bus RealTimeByFrequency City Taipei",
      "freshness": "fresh",
      "completeness": 1,
      "mode": "tdx-historical",
      "age": "0s",
      "x": "61.86%",
      "y": "51.11%"
    },
    {
      "PlateNumb": "EAA-087",
      "RouteUID": "TPE10231",
      "RouteName": "民權幹線",
      "Direction": 0,
      "BusPosition": {
        "PositionLat": 25.06259,
        "PositionLon": 121.528315
      },
      "Speed": 37,
      "Azimuth": 270,
      "GPSTime": "2026-05-20T06:54:35+08:00",
      "UpdateTime": "2026-05-20T06:54:45+08:00",
      "source": "TDX Historical Bus RealTimeByFrequency City Taipei",
      "freshness": "fresh",
      "completeness": 1,
      "mode": "tdx-historical",
      "age": "0s",
      "x": "48.92%",
      "y": "45.59%"
    },
    {
      "PlateNumb": "EAL-3078",
      "RouteUID": "TPE10241",
      "RouteName": "藍36",
      "Direction": 0,
      "BusPosition": {
        "PositionLat": 25.060317,
        "PositionLon": 121.591378
      },
      "Speed": 33,
      "Azimuth": 159,
      "GPSTime": "2026-05-20T06:54:39+08:00",
      "UpdateTime": "2026-05-20T06:54:45+08:00",
      "source": "TDX Historical Bus RealTimeByFrequency City Taipei",
      "freshness": "fresh",
      "completeness": 1,
      "mode": "tdx-historical",
      "age": "0s",
      "x": "73.69%",
      "y": "46.48%"
    },
    {
      "PlateNumb": "240-U5",
      "RouteUID": "TPE10293",
      "RouteName": "民生幹線",
      "Direction": 0,
      "BusPosition": {
        "PositionLat": 25.057958,
        "PositionLon": 121.533478
      },
      "Speed": 8,
      "Azimuth": 276,
      "GPSTime": "2026-05-20T06:54:37+08:00",
      "UpdateTime": "2026-05-20T06:54:45+08:00",
      "source": "TDX Historical Bus RealTimeByFrequency City Taipei",
      "freshness": "fresh",
      "completeness": 1,
      "mode": "tdx-historical",
      "age": "0s",
      "x": "50.95%",
      "y": "47.40%"
    },
    {
      "PlateNumb": "561-U5",
      "RouteUID": "TPE10181",
      "RouteName": "205",
      "Direction": 0,
      "BusPosition": {
        "PositionLat": 25.05181,
        "PositionLon": 121.583093
      },
      "Speed": 0,
      "Azimuth": 246,
      "GPSTime": "2026-05-20T06:54:31+08:00",
      "UpdateTime": "2026-05-20T06:54:45+08:00",
      "source": "TDX Historical Bus RealTimeByFrequency City Taipei",
      "freshness": "fresh",
      "completeness": 1,
      "mode": "tdx-historical",
      "age": "0s",
      "x": "70.43%",
      "y": "49.79%"
    },
    {
      "PlateNumb": "EAA-086",
      "RouteUID": "TPE10231",
      "RouteName": "民權幹線",
      "Direction": 0,
      "BusPosition": {
        "PositionLat": 25.068838,
        "PositionLon": 121.584592
      },
      "Speed": 0,
      "Azimuth": 264,
      "GPSTime": "2026-05-20T06:54:36+08:00",
      "UpdateTime": "2026-05-20T06:54:45+08:00",
      "source": "TDX Historical Bus RealTimeByFrequency City Taipei",
      "freshness": "fresh",
      "completeness": 1,
      "mode": "tdx-historical",
      "age": "0s",
      "x": "71.02%",
      "y": "43.15%"
    },
    {
      "PlateNumb": "EAL-1652",
      "RouteUID": "TPE10241",
      "RouteName": "藍36",
      "Direction": 0,
      "BusPosition": {
        "PositionLat": 25.066917,
        "PositionLon": 121.630453
      },
      "Speed": 18,
      "Azimuth": 321,
      "GPSTime": "2026-05-20T06:54:39+08:00",
      "UpdateTime": "2026-05-20T06:54:45+08:00",
      "source": "TDX Historical Bus RealTimeByFrequency City Taipei",
      "freshness": "fresh",
      "completeness": 1,
      "mode": "tdx-historical",
      "age": "0s",
      "x": "89.03%",
      "y": "43.90%"
    },
    {
      "PlateNumb": "KKC-1283",
      "RouteUID": "TPE10273",
      "RouteName": "303區",
      "Direction": 0,
      "BusPosition": {
        "PositionLat": 25.106713,
        "PositionLon": 121.535365
      },
      "Speed": 36,
      "Azimuth": 313,
      "GPSTime": "2026-05-20T06:54:39+08:00",
      "UpdateTime": "2026-05-20T06:54:45+08:00",
      "source": "TDX Historical Bus RealTimeByFrequency City Taipei",
      "freshness": "fresh",
      "completeness": 1,
      "mode": "tdx-historical",
      "age": "0s",
      "x": "51.69%",
      "y": "28.39%"
    },
    {
      "PlateNumb": "EAA-035",
      "RouteUID": "TPE10231",
      "RouteName": "民權幹線",
      "Direction": 1,
      "BusPosition": {
        "PositionLat": 25.0561,
        "PositionLon": 121.594195
      },
      "Speed": 8,
      "Azimuth": 315,
      "GPSTime": "2026-05-20T06:54:36+08:00",
      "UpdateTime": "2026-05-20T06:54:45+08:00",
      "source": "TDX Historical Bus RealTimeByFrequency City Taipei",
      "freshness": "fresh",
      "completeness": 1,
      "mode": "tdx-historical",
      "age": "0s",
      "x": "74.79%",
      "y": "48.12%"
    },
    {
      "PlateNumb": "EAL-3800",
      "RouteUID": "TPE10283",
      "RouteName": "235",
      "Direction": 0,
      "BusPosition": {
        "PositionLat": 25.01861,
        "PositionLon": 121.426935
      },
      "Speed": 4,
      "Azimuth": 58,
      "GPSTime": "2026-05-20T06:54:31+08:00",
      "UpdateTime": "2026-05-20T06:54:45+08:00",
      "source": "TDX Historical Bus RealTimeByFrequency City Taipei",
      "freshness": "fresh",
      "completeness": 1,
      "mode": "tdx-historical",
      "age": "0s",
      "x": "9.11%",
      "y": "62.73%"
    },
    {
      "PlateNumb": "EAL-2170",
      "RouteUID": "TPE10283",
      "RouteName": "235",
      "Direction": 0,
      "BusPosition": {
        "PositionLat": 25.033822,
        "PositionLon": 121.442288
      },
      "Speed": 15,
      "Azimuth": 97,
      "GPSTime": "2026-05-20T06:54:31+08:00",
      "UpdateTime": "2026-05-20T06:54:45+08:00",
      "source": "TDX Historical Bus RealTimeByFrequency City Taipei",
      "freshness": "fresh",
      "completeness": 1,
      "mode": "tdx-historical",
      "age": "0s",
      "x": "15.14%",
      "y": "56.80%"
    },
    {
      "PlateNumb": "EAL-2080",
      "RouteUID": "TPE10132",
      "RouteName": "234",
      "Direction": 0,
      "BusPosition": {
        "PositionLat": 24.9973,
        "PositionLon": 121.45724
      },
      "Speed": 0,
      "Azimuth": 24,
      "GPSTime": "2026-05-20T06:54:34+08:00",
      "UpdateTime": "2026-05-20T06:54:45+08:00",
      "source": "TDX Historical Bus RealTimeByFrequency City Taipei",
      "freshness": "fresh",
      "completeness": 1,
      "mode": "tdx-historical",
      "age": "0s",
      "x": "21.01%",
      "y": "71.04%"
    },
    {
      "PlateNumb": "EAL-5157",
      "RouteUID": "TPE10241",
      "RouteName": "藍36",
      "Direction": 0,
      "BusPosition": {
        "PositionLat": 25.067033,
        "PositionLon": 121.630395
      },
      "Speed": 13,
      "Azimuth": 317,
      "GPSTime": "2026-05-20T06:54:33+08:00",
      "UpdateTime": "2026-05-20T06:54:45+08:00",
      "source": "TDX Historical Bus RealTimeByFrequency City Taipei",
      "freshness": "fresh",
      "completeness": 1,
      "mode": "tdx-historical",
      "age": "0s",
      "x": "89.01%",
      "y": "43.86%"
    },
    {
      "PlateNumb": "611-U5",
      "RouteUID": "TPE10283",
      "RouteName": "235",
      "Direction": 0,
      "BusPosition": {
        "PositionLat": 25.029913,
        "PositionLon": 121.425922
      },
      "Speed": 10,
      "Azimuth": 348,
      "GPSTime": "2026-05-20T06:54:39+08:00",
      "UpdateTime": "2026-05-20T06:54:45+08:00",
      "source": "TDX Historical Bus RealTimeByFrequency City Taipei",
      "freshness": "fresh",
      "completeness": 1,
      "mode": "tdx-historical",
      "age": "0s",
      "x": "8.71%",
      "y": "58.33%"
    },
    {
      "PlateNumb": "EAL-3799",
      "RouteUID": "TPE10283",
      "RouteName": "235",
      "Direction": 0,
      "BusPosition": {
        "PositionLat": 25.01715,
        "PositionLon": 121.432777
      },
      "Speed": 39,
      "Azimuth": 181,
      "GPSTime": "2026-05-20T06:54:36+08:00",
      "UpdateTime": "2026-05-20T06:54:45+08:00",
      "source": "TDX Historical Bus RealTimeByFrequency City Taipei",
      "freshness": "fresh",
      "completeness": 1,
      "mode": "tdx-historical",
      "age": "0s",
      "x": "11.40%",
      "y": "63.30%"
    },
    {
      "PlateNumb": "697-U5",
      "RouteUID": "TPE10293",
      "RouteName": "民生幹線",
      "Direction": 0,
      "BusPosition": {
        "PositionLat": 25.051293,
        "PositionLon": 121.581718
      },
      "Speed": 0,
      "Azimuth": 353,
      "GPSTime": "2026-05-20T06:54:36+08:00",
      "UpdateTime": "2026-05-20T06:54:45+08:00",
      "source": "TDX Historical Bus RealTimeByFrequency City Taipei",
      "freshness": "fresh",
      "completeness": 1,
      "mode": "tdx-historical",
      "age": "0s",
      "x": "69.89%",
      "y": "49.99%"
    },
    {
      "PlateNumb": "EAL-3081",
      "RouteUID": "TPE10241",
      "RouteName": "藍36",
      "Direction": 1,
      "BusPosition": {
        "PositionLat": 25.062982,
        "PositionLon": 121.623427
      },
      "Speed": 0,
      "Azimuth": 249,
      "GPSTime": "2026-05-20T06:54:31+08:00",
      "UpdateTime": "2026-05-20T06:54:45+08:00",
      "source": "TDX Historical Bus RealTimeByFrequency City Taipei",
      "freshness": "fresh",
      "completeness": 1,
      "mode": "tdx-historical",
      "age": "0s",
      "x": "86.27%",
      "y": "45.44%"
    },
    {
      "PlateNumb": "EAA-378",
      "RouteUID": "TPE10278",
      "RouteName": "669",
      "Direction": 1,
      "BusPosition": {
        "PositionLat": 25.089452,
        "PositionLon": 121.488118
      },
      "Speed": 0,
      "Azimuth": 70,
      "GPSTime": "2026-05-20T06:54:35+08:00",
      "UpdateTime": "2026-05-20T06:54:45+08:00",
      "source": "TDX Historical Bus RealTimeByFrequency City Taipei",
      "freshness": "fresh",
      "completeness": 1,
      "mode": "tdx-historical",
      "age": "0s",
      "x": "33.14%",
      "y": "35.12%"
    },
    {
      "PlateNumb": "KKC-1285",
      "RouteUID": "TPE10273",
      "RouteName": "303區",
      "Direction": 1,
      "BusPosition": {
        "PositionLat": 25.143622,
        "PositionLon": 121.564223
      },
      "Speed": 0,
      "Azimuth": 304,
      "GPSTime": "2026-05-20T06:54:29+08:00",
      "UpdateTime": "2026-05-20T06:54:35+08:00",
      "source": "TDX Historical Bus RealTimeByFrequency City Taipei",
      "freshness": "fresh",
      "completeness": 1,
      "mode": "tdx-historical",
      "age": "0s",
      "x": "63.02%",
      "y": "14.00%"
    },
    {
      "PlateNumb": "243-U5",
      "RouteUID": "TPE10291",
      "RouteName": "棕1",
      "Direction": 0,
      "BusPosition": {
        "PositionLat": 25.05916,
        "PositionLon": 121.563432
      },
      "Speed": 25,
      "Azimuth": 287,
      "GPSTime": "2026-05-20T06:54:29+08:00",
      "UpdateTime": "2026-05-20T06:54:35+08:00",
      "source": "TDX Historical Bus RealTimeByFrequency City Taipei",
      "freshness": "fresh",
      "completeness": 1,
      "mode": "tdx-historical",
      "age": "0s",
      "x": "62.71%",
      "y": "46.93%"
    },
    {
      "PlateNumb": "693-U5",
      "RouteUID": "TPE10293",
      "RouteName": "民生幹線",
      "Direction": 0,
      "BusPosition": {
        "PositionLat": 25.058818,
        "PositionLon": 121.562037
      },
      "Speed": 37,
      "Azimuth": 259,
      "GPSTime": "2026-05-20T06:54:28+08:00",
      "UpdateTime": "2026-05-20T06:54:35+08:00",
      "source": "TDX Historical Bus RealTimeByFrequency City Taipei",
      "freshness": "fresh",
      "completeness": 1,
      "mode": "tdx-historical",
      "age": "0s",
      "x": "62.17%",
      "y": "47.06%"
    },
    {
      "PlateNumb": "EAL-2063",
      "RouteUID": "TPE10292",
      "RouteName": "藍10",
      "Direction": 0,
      "BusPosition": {
        "PositionLat": 25.04185,
        "PositionLon": 121.564958
      },
      "Speed": 0,
      "Azimuth": 209,
      "GPSTime": "2026-05-20T06:54:25+08:00",
      "UpdateTime": "2026-05-20T06:54:35+08:00",
      "source": "TDX Historical Bus RealTimeByFrequency City Taipei",
      "freshness": "fresh",
      "completeness": 1,
      "mode": "tdx-historical",
      "age": "0s",
      "x": "63.31%",
      "y": "53.68%"
    },
    {
      "PlateNumb": "EAL-2062",
      "RouteUID": "TPE10292",
      "RouteName": "藍10",
      "Direction": 0,
      "BusPosition": {
        "PositionLat": 25.067788,
        "PositionLon": 121.566955
      },
      "Speed": 0,
      "Azimuth": 336,
      "GPSTime": "2026-05-20T06:54:14+08:00",
      "UpdateTime": "2026-05-20T06:54:25+08:00",
      "source": "TDX Historical Bus RealTimeByFrequency City Taipei",
      "freshness": "fresh",
      "completeness": 1,
      "mode": "tdx-historical",
      "age": "0s",
      "x": "64.10%",
      "y": "43.56%"
    },
    {
      "PlateNumb": "698-U5",
      "RouteUID": "TPE10293",
      "RouteName": "民生幹線",
      "Direction": 0,
      "BusPosition": {
        "PositionLat": 25.05903,
        "PositionLon": 121.565397
      },
      "Speed": 29,
      "Azimuth": 266,
      "GPSTime": "2026-05-20T06:54:11+08:00",
      "UpdateTime": "2026-05-20T06:54:25+08:00",
      "source": "TDX Historical Bus RealTimeByFrequency City Taipei",
      "freshness": "fresh",
      "completeness": 1,
      "mode": "tdx-historical",
      "age": "0s",
      "x": "63.48%",
      "y": "46.98%"
    },
    {
      "PlateNumb": "692-U5",
      "RouteUID": "TPE10293",
      "RouteName": "民生幹線",
      "Direction": 1,
      "BusPosition": {
        "PositionLat": 25.059472,
        "PositionLon": 121.581172
      },
      "Speed": 29,
      "Azimuth": 231,
      "GPSTime": "2026-05-20T06:54:10+08:00",
      "UpdateTime": "2026-05-20T06:54:25+08:00",
      "source": "TDX Historical Bus RealTimeByFrequency City Taipei",
      "freshness": "fresh",
      "completeness": 1,
      "mode": "tdx-historical",
      "age": "0s",
      "x": "69.68%",
      "y": "46.81%"
    },
    {
      "PlateNumb": "EAL-2179",
      "RouteUID": "TPE10142",
      "RouteName": "南環幹線",
      "Direction": 0,
      "BusPosition": {
        "PositionLat": 25.024822,
        "PositionLon": 121.5757
      },
      "Speed": 84,
      "Azimuth": 330,
      "GPSTime": "2026-05-20T06:54:04+08:00",
      "UpdateTime": "2026-05-20T06:54:15+08:00",
      "source": "TDX Historical Bus RealTimeByFrequency City Taipei",
      "freshness": "fresh",
      "completeness": 1,
      "mode": "tdx-historical",
      "age": "0s",
      "x": "67.53%",
      "y": "60.31%"
    },
    {
      "PlateNumb": "629-U5",
      "RouteUID": "TPE10293",
      "RouteName": "民生幹線",
      "Direction": 0,
      "BusPosition": {
        "PositionLat": 25.057023,
        "PositionLon": 121.514015
      },
      "Speed": 0,
      "Azimuth": 276,
      "GPSTime": "2026-05-20T06:54:05+08:00",
      "UpdateTime": "2026-05-20T06:54:15+08:00",
      "source": "TDX Historical Bus RealTimeByFrequency City Taipei",
      "freshness": "fresh",
      "completeness": 1,
      "mode": "tdx-historical",
      "age": "0s",
      "x": "43.31%",
      "y": "47.76%"
    },
    {
      "PlateNumb": "651-U5",
      "RouteUID": "TPE10293",
      "RouteName": "民生幹線",
      "Direction": 1,
      "BusPosition": {
        "PositionLat": 25.062025,
        "PositionLon": 121.582422
      },
      "Speed": 0,
      "Azimuth": 60,
      "GPSTime": "2026-05-20T06:53:58+08:00",
      "UpdateTime": "2026-05-20T06:54:05+08:00",
      "source": "TDX Historical Bus RealTimeByFrequency City Taipei",
      "freshness": "fresh",
      "completeness": 1,
      "mode": "tdx-historical",
      "age": "0s",
      "x": "70.17%",
      "y": "45.81%"
    },
    {
      "PlateNumb": "EAA-051",
      "RouteUID": "TPE10231",
      "RouteName": "民權幹線",
      "Direction": 0,
      "BusPosition": {
        "PositionLat": 25.056152,
        "PositionLon": 121.594328
      },
      "Speed": 0,
      "Azimuth": 294,
      "GPSTime": "2026-05-20T06:53:24+08:00",
      "UpdateTime": "2026-05-20T06:53:35+08:00",
      "source": "TDX Historical Bus RealTimeByFrequency City Taipei",
      "freshness": "fresh",
      "completeness": 1,
      "mode": "tdx-historical",
      "age": "0s",
      "x": "74.85%",
      "y": "48.10%"
    },
    {
      "PlateNumb": "EAL-1180",
      "RouteUID": "TPE10231",
      "RouteName": "民權幹線",
      "Direction": 0,
      "BusPosition": {
        "PositionLat": 25.069108,
        "PositionLon": 121.588728
      },
      "Speed": 38,
      "Azimuth": 273,
      "GPSTime": "2026-05-20T06:53:07+08:00",
      "UpdateTime": "2026-05-20T06:53:15+08:00",
      "source": "TDX Historical Bus RealTimeByFrequency City Taipei",
      "freshness": "fresh",
      "completeness": 1,
      "mode": "tdx-historical",
      "age": "0s",
      "x": "72.65%",
      "y": "43.05%"
    },
    {
      "PlateNumb": "650-U5",
      "RouteUID": "TPE10283",
      "RouteName": "235",
      "Direction": 0,
      "BusPosition": {
        "PositionLat": 25.0201,
        "PositionLon": 121.434825
      },
      "Speed": 0,
      "Azimuth": 336,
      "GPSTime": "2026-05-20T06:52:32+08:00",
      "UpdateTime": "2026-05-20T06:52:45+08:00",
      "source": "TDX Historical Bus RealTimeByFrequency City Taipei",
      "freshness": "fresh",
      "completeness": 1,
      "mode": "tdx-historical",
      "age": "0s",
      "x": "12.21%",
      "y": "62.15%"
    },
    {
      "PlateNumb": "EAL-3170",
      "RouteUID": "TPE10251",
      "RouteName": "南京幹線",
      "Direction": 0,
      "BusPosition": {
        "PositionLat": 25.052423,
        "PositionLon": 121.52093
      },
      "Speed": 0,
      "Azimuth": 282,
      "GPSTime": "2026-05-20T06:49:29+08:00",
      "UpdateTime": "2026-05-20T06:49:35+08:00",
      "source": "TDX Historical Bus RealTimeByFrequency City Taipei carried forward 30m",
      "freshness": "fresh",
      "completeness": 1,
      "mode": "tdx-historical-carried",
      "age": "25s",
      "x": "46.02%",
      "y": "49.55%"
    },
    {
      "PlateNumb": "EAA-085",
      "RouteUID": "TPE10231",
      "RouteName": "民權幹線",
      "Direction": 1,
      "BusPosition": {
        "PositionLat": 25.056182,
        "PositionLon": 121.59419
      },
      "Speed": 0,
      "Azimuth": 74,
      "GPSTime": "2026-05-20T06:47:47+08:00",
      "UpdateTime": "2026-05-20T06:47:55+08:00",
      "source": "TDX Historical Bus RealTimeByFrequency City Taipei carried forward 30m",
      "freshness": "fresh",
      "completeness": 1,
      "mode": "tdx-historical-carried",
      "age": "125s",
      "x": "74.79%",
      "y": "48.09%"
    },
    {
      "PlateNumb": "EAA-050",
      "RouteUID": "TPE10231",
      "RouteName": "民權幹線",
      "Direction": 1,
      "BusPosition": {
        "PositionLat": 25.060647,
        "PositionLon": 121.51443
      },
      "Speed": 2,
      "Azimuth": 343,
      "GPSTime": "2026-05-20T06:43:26+08:00",
      "UpdateTime": "2026-05-20T06:43:35+08:00",
      "source": "TDX Historical Bus RealTimeByFrequency City Taipei carried forward 30m",
      "freshness": "fresh",
      "completeness": 1,
      "mode": "tdx-historical-carried",
      "age": "385s",
      "x": "43.47%",
      "y": "46.35%"
    },
    {
      "PlateNumb": "KKC-1282",
      "RouteUID": "TPE10272",
      "RouteName": "303",
      "Direction": 1,
      "BusPosition": {
        "PositionLat": 25.085812,
        "PositionLon": 121.524907
      },
      "Speed": 1,
      "Azimuth": 163,
      "GPSTime": "2026-05-20T06:41:59+08:00",
      "UpdateTime": "2026-05-20T06:42:05+08:00",
      "source": "TDX Historical Bus RealTimeByFrequency City Taipei carried forward 30m",
      "freshness": "fresh",
      "completeness": 1,
      "mode": "tdx-historical-carried",
      "age": "475s",
      "x": "47.58%",
      "y": "36.54%"
    },
    {
      "PlateNumb": "EAL-3176",
      "RouteUID": "TPE10251",
      "RouteName": "南京幹線",
      "Direction": 0,
      "BusPosition": {
        "PositionLat": 25.053168,
        "PositionLon": 121.518207
      },
      "Speed": 0,
      "Azimuth": 285,
      "GPSTime": "2026-05-20T06:39:24+08:00",
      "UpdateTime": "2026-05-20T06:39:35+08:00",
      "source": "TDX Historical Bus RealTimeByFrequency City Taipei carried forward 30m",
      "freshness": "fresh",
      "completeness": 1,
      "mode": "tdx-historical-carried",
      "age": "625s",
      "x": "44.95%",
      "y": "49.26%"
    },
    {
      "PlateNumb": "626-U5",
      "RouteUID": "TPE10283",
      "RouteName": "235",
      "Direction": 1,
      "BusPosition": {
        "PositionLat": 25.01916,
        "PositionLon": 121.433242
      },
      "Speed": 42,
      "Azimuth": 23,
      "GPSTime": "2026-05-20T06:39:24+08:00",
      "UpdateTime": "2026-05-20T06:39:35+08:00",
      "source": "TDX Historical Bus RealTimeByFrequency City Taipei carried forward 30m",
      "freshness": "fresh",
      "completeness": 1,
      "mode": "tdx-historical-carried",
      "age": "625s",
      "x": "11.59%",
      "y": "62.52%"
    },
    {
      "PlateNumb": "736-FW",
      "RouteUID": "TPE10283",
      "RouteName": "235",
      "Direction": 0,
      "BusPosition": {
        "PositionLat": 25.017947,
        "PositionLon": 121.432877
      },
      "Speed": 34,
      "Azimuth": 3,
      "GPSTime": "2026-05-20T06:25:25+08:00",
      "UpdateTime": "2026-05-20T06:25:35+08:00",
      "source": "TDX Historical Bus RealTimeByFrequency City Taipei carried forward 30m",
      "freshness": "fresh",
      "completeness": 1,
      "mode": "tdx-historical-carried",
      "age": "1465s",
      "x": "11.44%",
      "y": "62.99%"
    }
  ]
}
